datenraffinerie/__init__.py
datenraffinerie/acquire_data.py
datenraffinerie/analysis_utilities.py
datenraffinerie/config_errors.py
datenraffinerie/config_utilities.py
datenraffinerie/config_validators.py
datenraffinerie/control_adapter.py
datenraffinerie/daq_coordination.py
datenraffinerie/datenraffinerie.py
datenraffinerie/dict_utils.py
datenraffinerie/distillery.py
datenraffinerie/errors.py
datenraffinerie/frack_data.py
datenraffinerie/fracker.py
datenraffinerie/full_daq.py
datenraffinerie/gen_configurations.py
datenraffinerie/hdf_utils.py
datenraffinerie/luigi_utils.py
datenraffinerie/postprocessing_queue.py
datenraffinerie/print_h5.py
datenraffinerie/read_rocs.py
datenraffinerie/scan.py
datenraffinerie/valve_yard.py
datenraffinerie/vlvyrd_utils.py
datenraffinerie/yaml_utils.py
datenraffinerie/zmq_controler.py
datenraffinerie-1.0.15.dist-info/LICENSE
datenraffinerie-1.0.15.dist-info/METADATA
datenraffinerie-1.0.15.dist-info/WHEEL
datenraffinerie-1.0.15.dist-info/entry_points.txt
datenraffinerie-1.0.15.dist-info/top_level.txt
datenraffinerie-1.0.15.dist-info/RECORD
