Metadata-Version: 2.1
Name: datenraffinerie
Version: 1.0.15
Summary: Toolset to acqire and process Data from test systems of the HGCAL detector
Classifier: Programming Language :: Python :: 3
Classifier: License :: OSI Approved :: GNU General Public License v3 (GPLv3)
Classifier: Operating System :: POSIX :: Linux
Classifier: Environment :: Console
Requires-Python: >=3.9
License-File: LICENSE
Requires-Dist: click (==8.1.3)
Requires-Dist: pandas (==1.5.1)
Requires-Dist: numpy (==1.23.4)
Requires-Dist: pyYAML (==6.0)
Requires-Dist: zmq (==0.0.0)
Requires-Dist: pyzmq (==24.0.1)
Requires-Dist: pytest (==7.2.0)
Requires-Dist: tables (==3.7.0)
Requires-Dist: Jinja2 (==3.1.2)
Requires-Dist: schema (==0.7.5)
Requires-Dist: rich (==12.6.0)
Requires-Dist: pymongo (==4.3.2)
Requires-Dist: hgcroc-configuration-client (==1.2.1)
